kubernetes_asyncio/__init__.py
kubernetes_asyncio/client/__init__.py
kubernetes_asyncio/client/api_client.py
kubernetes_asyncio/client/configuration.py
kubernetes_asyncio/client/exceptions.py
kubernetes_asyncio/client/rest.py
kubernetes_asyncio/client/test_rest.py
kubernetes_asyncio/client/api/__init__.py
kubernetes_asyncio/client/api/admissionregistration_api.py
kubernetes_asyncio/client/api/admissionregistration_v1_api.py
kubernetes_asyncio/client/api/admissionregistration_v1alpha1_api.py
kubernetes_asyncio/client/api/admissionregistration_v1beta1_api.py
kubernetes_asyncio/client/api/apiextensions_api.py
kubernetes_asyncio/client/api/apiextensions_v1_api.py
kubernetes_asyncio/client/api/apiregistration_api.py
kubernetes_asyncio/client/api/apiregistration_v1_api.py
kubernetes_asyncio/client/api/apis_api.py
kubernetes_asyncio/client/api/apps_api.py
kubernetes_asyncio/client/api/apps_v1_api.py
kubernetes_asyncio/client/api/authentication_api.py
kubernetes_asyncio/client/api/authentication_v1_api.py
kubernetes_asyncio/client/api/authentication_v1alpha1_api.py
kubernetes_asyncio/client/api/authentication_v1beta1_api.py
kubernetes_asyncio/client/api/authorization_api.py
kubernetes_asyncio/client/api/authorization_v1_api.py
kubernetes_asyncio/client/api/autoscaling_api.py
kubernetes_asyncio/client/api/autoscaling_v1_api.py
kubernetes_asyncio/client/api/autoscaling_v2_api.py
kubernetes_asyncio/client/api/batch_api.py
kubernetes_asyncio/client/api/batch_v1_api.py
kubernetes_asyncio/client/api/certificates_api.py
kubernetes_asyncio/client/api/certificates_v1_api.py
kubernetes_asyncio/client/api/certificates_v1alpha1_api.py
kubernetes_asyncio/client/api/coordination_api.py
kubernetes_asyncio/client/api/coordination_v1_api.py
kubernetes_asyncio/client/api/coordination_v1alpha1_api.py
kubernetes_asyncio/client/api/coordination_v1alpha2_api.py
kubernetes_asyncio/client/api/core_api.py
kubernetes_asyncio/client/api/core_v1_api.py
kubernetes_asyncio-32.3.1.dist-info/licenses/LICENSE
kubernetes_asyncio-32.3.1.dist-info/METADATA
kubernetes_asyncio-32.3.1.dist-info/WHEEL
kubernetes_asyncio-32.3.1.dist-info/top_level.txt
kubernetes_asyncio-32.3.1.dist-info/RECORD
