Metadata-Version: 2.4
Name: kubernetes_asyncio
Version: 32.3.1
Summary: Kubernetes asynchronous python client
Home-page: https://github.com/tomplus/kubernetes_asyncio
Author: Kubernetes
Author-email: 
License: Apache License Version 2.0
Keywords: Swagger,OpenAPI,Kubernetes
Classifier: Development Status :: 5 - Production/Stable
Classifier: Topic :: Utilities
Classifier: Intended Audience :: Developers
Classifier: Intended Audience :: Information Technology
Classifier: License :: OSI Approved :: Apache Software License
Classifier: Operating System :: OS Independent
Classifier: Programming Language :: Python
Classifier: Programming Language :: Python :: 3
Classifier: Programming Language :: Python :: 3.6
Classifier: Programming Language :: Python :: 3.7
Classifier: Programming Language :: Python :: 3.8
Classifier: Programming Language :: Python :: 3.9
Classifier: Programming Language :: Python :: 3.10
Classifier: Programming Language :: Python :: 3.11
Classifier: Programming Language :: Python :: 3.12
License-File: LICENSE
Requires-Dist: certifi>=14.05.14
Requires-Dist: six>=1.9.0
Requires-Dist: python-dateutil>=2.5.3
Requires-Dist: urllib3>=1.24.2
Requires-Dist: pyyaml>=3.12
Requires-Dist: aiohttp<4.0.0,>=3.9.0
Dynamic: author
Dynamic: classifier
Dynamic: description
Dynamic: home-page
Dynamic: keywords
Dynamic: license
Dynamic: license-file
Dynamic: requires-dist
Dynamic: summary
